kinnaird_utils/__init__.py
kinnaird_utils/constants.py
kinnaird_utils/containers.py
kinnaird_utils/file_utils.py
kinnaird_utils/folders.py
kinnaird_utils/log_formatting.py
kinnaird_utils/print_utils.py
kinnaird_utils/shell.py
kinnaird_utils/system_processes.py
kinnaird_utils/testing_utils.py
kinnaird_utils/text_parser_utils.py
kinnaird_utils/time.py
kinnaird_utils/version.py
kinnaird_utils/aws/__init__.py
kinnaird_utils/aws/ecr.py
kinnaird_utils/aws/general.py
kinnaird_utils/aws/lambda_functions.py
kinnaird_utils/aws/login.py
kinnaird_utils/aws/s3.py
kinnaird_utils/aws/sns.py
kinnaird_utils-0.0.28.dist-info/LICENSE
kinnaird_utils-0.0.28.dist-info/METADATA
kinnaird_utils-0.0.28.dist-info/WHEEL
kinnaird_utils-0.0.28.dist-info/top_level.txt
kinnaird_utils-0.0.28.dist-info/zip-safe
kinnaird_utils-0.0.28.dist-info/RECORD
