Metadata-Version: 2.1
Name: kinnaird-utils
Version: 0.0.28
Summary: UNKNOWN
Home-page: https://github.com/kmcquade/kinnaird-utils
Author: Kinnaird McQuade
Author-email: kinnairdm@gmail.com
License: UNKNOWN
Project-URL: Documentation, https://policy-sentry.readthedocs.io/
Project-URL: Code, https://github.com/salesforce/policy_sentry/
Project-URL: Example Report, https://opensource.salesforce.com/cloudsplaining
Project-URL: Twitter, https://twitter.com/kmcquade3
Project-URL: Red Team Report, https://kmcquade.com/security.html
Keywords: kinnaird
Platform: UNKNOWN
Classifier: Programming Language :: Python :: 3
Classifier: License :: OSI Approved :: MIT License
Classifier: Operating System :: OS Independent
Requires-Python: >=3.7
Requires-Dist: pyyaml
Requires-Dist: click
Requires-Dist: pydantic
Requires-Dist: boto3
Requires-Dist: botocore
Requires-Dist: aws-lambda-powertools
Requires-Dist: colorama
